MANIFEST.in
NEWS.rst
README.rst
setup.py
src/jig/__init__.py
src/jig/backports.py
src/jig/conf.py
src/jig/diffconvert.py
src/jig/entrypoints.py
src/jig/exc.py
src/jig/gitutils.py
src/jig/output.py
src/jig/runner.py
src/jig/tools.py
src/jig.egg-info/PKG-INFO
src/jig.egg-info/SOURCES.txt
src/jig.egg-info/dependency_links.txt
src/jig.egg-info/entry_points.txt
src/jig.egg-info/not-zip-safe
src/jig.egg-info/requires.txt
src/jig.egg-info/top_level.txt
src/jig/commands/__init__.py
src/jig/commands/base.py
src/jig/commands/config.py
src/jig/commands/hints.py
src/jig/commands/init.py
src/jig/commands/install.py
src/jig/commands/plugin.py
src/jig/commands/report.py
src/jig/commands/runnow.py
src/jig/commands/sticky.py
src/jig/commands/version.py
src/jig/commands/tests/__init__.py
src/jig/commands/tests/test_commands.py
src/jig/commands/tests/test_config.py
src/jig/commands/tests/test_init.py
src/jig/commands/tests/test_install.py
src/jig/commands/tests/test_plugin.py
src/jig/commands/tests/test_report.py
src/jig/commands/tests/test_runnow.py
src/jig/commands/tests/test_sticky.py
src/jig/commands/tests/test_version.py
src/jig/data/pre-commits/python
src/jig/gitutils/__init__.py
src/jig/gitutils/branches.py
src/jig/gitutils/checks.py
src/jig/gitutils/hooking.py
src/jig/gitutils/remote.py
src/jig/gitutils/scripts.py
src/jig/gitutils/tests/__init__.py
src/jig/gitutils/tests/test_branches.py
src/jig/gitutils/tests/test_checks.py
src/jig/gitutils/tests/test_hooking.py
src/jig/gitutils/tests/test_remote.py
src/jig/packages/__init__.py
src/jig/packages/argparse/__init__.py
src/jig/packages/argparse/argparse.py
src/jig/plugins/__init__.py
src/jig/plugins/manager.py
src/jig/plugins/testrunner.py
src/jig/plugins/tools.py
src/jig/plugins/tests/__init__.py
src/jig/plugins/tests/test_manager.py
src/jig/plugins/tests/test_parse_range.py
src/jig/plugins/tests/test_testrunner.py
src/jig/plugins/tests/test_tools.py
src/jig/tests/__init__.py
src/jig/tests/mocks.py
src/jig/tests/noseplugin.py
src/jig/tests/test_diffconvert.py
src/jig/tests/test_mocks.py
src/jig/tests/test_output.py
src/jig/tests/test_runner.py
src/jig/tests/test_tools.py
src/jig/tests/testcase.py