Metadata-Version: 1.1
Name: jig
Version: 0.1.11
Summary: Check your code for stuff before you `git commit`
Home-page: http://github.com/robmadole/jig
Author: Rob Madole
Author-email: robmadole@gmail.com
License: MIT
Keywords: git hooks code smell lint
Platform: UNKNOWN
Classifier: Development Status :: 4 - Beta
Classifier: Environment :: Console
Classifier: License :: OSI Approved :: MIT License
Classifier: Intended Audience :: Developers
Classifier: Natural Language :: English
Classifier: Operating System :: POSIX
Classifier: Programming Language :: Python :: 2.6
Classifier: Programming Language :: Python :: 2.7
Classifier: Topic :: Software Development :: Quality Assurance
Classifier: Topic :: Software Development :: Version Control
Classifier: Topic :: Text Processing
